{"gui_kwd": "2", "assignmentId": "0", "gd_kwd": "2", "easy_acc": "1", "train_acc": "0.75", "output": [{"time_spent": 8990, "selection": "B", "triplet_id": 0}, {"time_spent": 2641, "selection": "B", "triplet_id": 1}, {"time_spent": 2311, "selection": "B", "triplet_id": 2}, {"time_spent": 1961, "selection": "A", "triplet_id": 3}, {"time_spent": 4727, "selection": "B", "triplet_id": 4}, {"time_spent": 4856, "selection": "B", "triplet_id": 5}, {"time_spent": 3345, "selection": "A", "triplet_id": 6}, {"time_spent": 5175, "selection": "A", "triplet_id": 7}, {"time_spent": 4272, "selection": "A", "triplet_id": 8}, {"time_spent": 3128, "selection": "B", "triplet_id": 9}, {"time_spent": 1768, "selection": "B", "triplet_id": 10}, {"time_spent": 3856, "selection": "A", "triplet_id": 11}, {"time_spent": 2112, "selection": "A", "triplet_id": 12}, {"time_spent": 2816, "selection": "A", "triplet_id": 13}, {"time_spent": 5024, "selection": "B", "triplet_id": 14}, {"time_spent": 10785, "selection": "B", "triplet_id": 15}, {"time_spent": 2831, "selection": "A", "triplet_id": 16}, {"time_spent": 4056, "selection": "A", "triplet_id": 17}, {"time_spent": 4000, "selection": "B", "triplet_id": 18}, {"time_spent": 2417, "selection": "A", "triplet_id": 19}, {"time_spent": 2935, "selection": "B", "triplet_id": 20}, {"time_spent": 3616, "selection": "A", "triplet_id": 21}, {"time_spent": 1680, "selection": "B", "triplet_id": 22}, {"time_spent": 9009, "selection": "A", "triplet_id": 23}, {"time_spent": 4359, "selection": "B", "triplet_id": 24}, {"time_spent": 1680, "selection": "A", "triplet_id": 25}, {"time_spent": 2272, "selection": "B", "triplet_id": 26}, {"time_spent": 3968, "selection": "B", "triplet_id": 27}, {"time_spent": 3216, "selection": "A", "triplet_id": 28}, {"time_spent": 1769, "selection": "B", "triplet_id": 29}, {"time_spent": 2463, "selection": "B", "triplet_id": 30}, {"time_spent": 3585, "selection": "A", "triplet_id": 31}, {"time_spent": 4199, "selection": "B", "triplet_id": 32}, {"time_spent": 2032, "selection": "A", "triplet_id": 33}, {"time_spent": 3504, "selection": "B", "triplet_id": 34}, {"time_spent": 2929, "selection": "A", "triplet_id": 35}, {"time_spent": 1599, "selection": "B", "triplet_id": 36}, {"time_spent": 3072, "selection": "A", "triplet_id": 37}, {"time_spent": 1680, "selection": "A", "triplet_id": 38}, {"time_spent": 2456, "selection": "B", "triplet_id": 39}, {"time_spent": 2656, "selection": "A", "triplet_id": 40}, {"time_spent": 1744, "selection": "B", "triplet_id": 41}, {"time_spent": 1857, "selection": "A", "triplet_id": 42}, {"time_spent": 2336, "selection": "A", "triplet_id": 43}, {"time_spent": 1663, "selection": "A", "triplet_id": 44}, {"time_spent": 3400, "selection": "B", "triplet_id": 45}, {"time_spent": 2016, "selection": "B", "triplet_id": 46}, {"time_spent": 3104, "selection": "A", "triplet_id": 47}, {"time_spent": 3040, "selection": "B", "triplet_id": 48}, {"time_spent": 1793, "selection": "B", "triplet_id": 49}, {"time_spent": 2088, "selection": "B", "triplet_id": 50}, {"time_spent": 2079, "selection": "A", "triplet_id": 51}, {"time_spent": 1768, "selection": "B", "triplet_id": 52}, {"time_spent": 7488, "selection": "A", "triplet_id": 53}, {"time_spent": 3584, "selection": "B", "triplet_id": 54}, {"time_spent": 1617, "selection": "A", "triplet_id": 55}, {"time_spent": 2343, "selection": "B", "triplet_id": 56}, {"time_spent": 3200, "selection": "A", "triplet_id": 57}, {"time_spent": 2064, "selection": "B", "triplet_id": 58}, {"time_spent": 2128, "selection": "B", "triplet_id": 59}], "gen": "F"}
{"gui_kwd": "2", "assignmentId": "1", "gd_kwd": "1", "easy_acc": "0.8571428571428571", "train_acc": "1", "output": [{"time_spent": 4684, "selection": "A", "triplet_id": 0}, {"time_spent": 2946, "selection": "B", "triplet_id": 1}, {"time_spent": 3384, "selection": "B", "triplet_id": 2}, {"time_spent": 4062, "selection": "B", "triplet_id": 3}, {"time_spent": 1990, "selection": "B", "triplet_id": 4}, {"time_spent": 2072, "selection": "A", "triplet_id": 5}, {"time_spent": 6721, "selection": "A", "triplet_id": 6}, {"time_spent": 4918, "selection": "B", "triplet_id": 7}, {"time_spent": 2286, "selection": "A", "triplet_id": 8}, {"time_spent": 3388, "selection": "B", "triplet_id": 9}, {"time_spent": 2324, "selection": "A", "triplet_id": 10}, {"time_spent": 2981, "selection": "A", "triplet_id": 11}, {"time_spent": 3835, "selection": "A", "triplet_id": 12}, {"time_spent": 3465, "selection": "A", "triplet_id": 13}, {"time_spent": 3836, "selection": "A", "triplet_id": 14}, {"time_spent": 2880, "selection": "B", "triplet_id": 15}, {"time_spent": 5948, "selection": "A", "triplet_id": 16}, {"time_spent": 2218, "selection": "A", "triplet_id": 17}, {"time_spent": 6150, "selection": "A", "triplet_id": 18}, {"time_spent": 4663, "selection": "A", "triplet_id": 19}, {"time_spent": 9800, "selection": "A", "triplet_id": 20}, {"time_spent": 3712, "selection": "A", "triplet_id": 21}, {"time_spent": 3008, "selection": "A", "triplet_id": 22}, {"time_spent": 3224, "selection": "A", "triplet_id": 23}, {"time_spent": 3184, "selection": "B", "triplet_id": 24}, {"time_spent": 2225, "selection": "B", "triplet_id": 25}, {"time_spent": 2890, "selection": "A", "triplet_id": 26}, {"time_spent": 11554, "selection": "B", "triplet_id": 27}, {"time_spent": 2594, "selection": "B", "triplet_id": 28}, {"time_spent": 2316, "selection": "A", "triplet_id": 29}, {"time_spent": 2674, "selection": "B", "triplet_id": 30}, {"time_spent": 2134, "selection": "A", "triplet_id": 31}, {"time_spent": 3346, "selection": "B", "triplet_id": 32}, {"time_spent": 4057, "selection": "A", "triplet_id": 33}, {"time_spent": 7726, "selection": "B", "triplet_id": 34}, {"time_spent": 2536, "selection": "A", "triplet_id": 35}, {"time_spent": 3682, "selection": "A", "triplet_id": 36}, {"time_spent": 7171, "selection": "B", "triplet_id": 37}, {"time_spent": 3568, "selection": "A", "triplet_id": 38}, {"time_spent": 2696, "selection": "B", "triplet_id": 39}, {"time_spent": 2738, "selection": "B", "triplet_id": 40}, {"time_spent": 4666, "selection": "B", "triplet_id": 41}, {"time_spent": 3914, "selection": "A", "triplet_id": 42}, {"time_spent": 2610, "selection": "B", "triplet_id": 43}, {"time_spent": 2824, "selection": "A", "triplet_id": 44}, {"time_spent": 14287, "selection": "B", "triplet_id": 45}, {"time_spent": 2262, "selection": "B", "triplet_id": 46}, {"time_spent": 7769, "selection": "B", "triplet_id": 47}, {"time_spent": 4621, "selection": "A", "triplet_id": 48}, {"time_spent": 1810, "selection": "A", "triplet_id": 49}, {"time_spent": 5348, "selection": "A", "triplet_id": 50}, {"time_spent": 4164, "selection": "A", "triplet_id": 51}, {"time_spent": 2600, "selection": "B", "triplet_id": 52}, {"time_spent": 4742, "selection": "A", "triplet_id": 53}, {"time_spent": 1901, "selection": "A", "triplet_id": 54}, {"time_spent": 4818, "selection": "B", "triplet_id": 55}, {"time_spent": 2622, "selection": "B", "triplet_id": 56}, {"time_spent": 5876, "selection": "A", "triplet_id": 57}, {"time_spent": 6458, "selection": "B", "triplet_id": 58}, {"time_spent": 3449, "selection": "A", "triplet_id": 59}], "gen": "M"}
{"gui_kwd": "2", "assignmentId": "3", "gd_kwd": "2", "easy_acc": "0.7142857142857143", "train_acc": "1", "output": [{"time_spent": 7894, "selection": "B", "triplet_id": 0}, {"time_spent": 7472, "selection": "B", "triplet_id": 1}, {"time_spent": 3954, "selection": "A", "triplet_id": 2}, {"time_spent": 2876, "selection": "A", "triplet_id": 3}, {"time_spent": 9044, "selection": "B", "triplet_id": 4}, {"time_spent": 4520, "selection": "B", "triplet_id": 5}, {"time_spent": 2957, "selection": "A", "triplet_id": 6}, {"time_spent": 9240, "selection": "B", "triplet_id": 7}, {"time_spent": 4875, "selection": "A", "triplet_id": 8}, {"time_spent": 22440, "selection": "B", "triplet_id": 9}, {"time_spent": 3878, "selection": "A", "triplet_id": 10}, {"time_spent": 2600, "selection": "A", "triplet_id": 11}, {"time_spent": 2216, "selection": "B", "triplet_id": 12}, {"time_spent": 4156, "selection": "A", "triplet_id": 13}, {"time_spent": 5769, "selection": "A", "triplet_id": 14}, {"time_spent": 4660, "selection": "A", "triplet_id": 15}, {"time_spent": 4712, "selection": "A", "triplet_id": 16}, {"time_spent": 2402, "selection": "B", "triplet_id": 17}, {"time_spent": 8266, "selection": "B", "triplet_id": 18}, {"time_spent": 4718, "selection": "B", "triplet_id": 19}, {"time_spent": 5286, "selection": "B", "triplet_id": 20}, {"time_spent": 7058, "selection": "A", "triplet_id": 21}, {"time_spent": 3360, "selection": "A", "triplet_id": 22}, {"time_spent": 2592, "selection": "A", "triplet_id": 23}, {"time_spent": 3682, "selection": "A", "triplet_id": 24}, {"time_spent": 5573, "selection": "B", "triplet_id": 25}, {"time_spent": 2673, "selection": "A", "triplet_id": 26}, {"time_spent": 2654, "selection": "B", "triplet_id": 27}, {"time_spent": 7167, "selection": "A", "triplet_id": 28}, {"time_spent": 2194, "selection": "B", "triplet_id": 29}, {"time_spent": 3234, "selection": "A", "triplet_id": 30}, {"time_spent": 4367, "selection": "A", "triplet_id": 31}, {"time_spent": 5562, "selection": "A", "triplet_id": 32}, {"time_spent": 3470, "selection": "A", "triplet_id": 33}, {"time_spent": 7427, "selection": "B", "triplet_id": 34}, {"time_spent": 2986, "selection": "A", "triplet_id": 35}, {"time_spent": 4312, "selection": "B", "triplet_id": 36}, {"time_spent": 5813, "selection": "B", "triplet_id": 37}, {"time_spent": 5489, "selection": "B", "triplet_id": 38}, {"time_spent": 5695, "selection": "A", "triplet_id": 39}, {"time_spent": 2894, "selection": "B", "triplet_id": 40}, {"time_spent": 4308, "selection": "B", "triplet_id": 41}, {"time_spent": 5412, "selection": "A", "triplet_id": 42}, {"time_spent": 2412, "selection": "B", "triplet_id": 43}, {"time_spent": 28916, "selection": "B", "triplet_id": 44}, {"time_spent": 15569, "selection": "B", "triplet_id": 45}, {"time_spent": 2599, "selection": "A", "triplet_id": 46}, {"time_spent": 3863, "selection": "B", "triplet_id": 47}, {"time_spent": 4272, "selection": "B", "triplet_id": 48}, {"time_spent": 3082, "selection": "B", "triplet_id": 49}, {"time_spent": 3052, "selection": "B", "triplet_id": 50}, {"time_spent": 3506, "selection": "A", "triplet_id": 51}, {"time_spent": 4918, "selection": "B", "triplet_id": 52}, {"time_spent": 4874, "selection": "A", "triplet_id": 53}, {"time_spent": 2296, "selection": "A", "triplet_id": 54}, {"time_spent": 3147, "selection": "A", "triplet_id": 55}, {"time_spent": 3637, "selection": "A", "triplet_id": 56}, {"time_spent": 6189, "selection": "A", "triplet_id": 57}, {"time_spent": 3669, "selection": "B", "triplet_id": 58}, {"time_spent": 14300, "selection": "B", "triplet_id": 59}], "gen": "M"}
{"gui_kwd": "4", "assignmentId": "5", "gd_kwd": "3", "easy_acc": "0.8571428571428571", "train_acc": "1", "output": [{"time_spent": 5331, "selection": "A", "triplet_id": 0}, {"time_spent": 5708, "selection": "A", "triplet_id": 1}, {"time_spent": 7947, "selection": "B", "triplet_id": 2}, {"time_spent": 5330, "selection": "A", "triplet_id": 3}, {"time_spent": 8092, "selection": "B", "triplet_id": 4}, {"time_spent": 6736, "selection": "A", "triplet_id": 5}, {"time_spent": 4852, "selection": "A", "triplet_id": 6}, {"time_spent": 4821, "selection": "A", "triplet_id": 7}, {"time_spent": 7649, "selection": "B", "triplet_id": 8}, {"time_spent": 6330, "selection": "A", "triplet_id": 9}, {"time_spent": 7967, "selection": "B", "triplet_id": 10}, {"time_spent": 4382, "selection": "B", "triplet_id": 11}, {"time_spent": 7039, "selection": "B", "triplet_id": 12}, {"time_spent": 6345, "selection": "B", "triplet_id": 13}, {"time_spent": 3317, "selection": "B", "triplet_id": 14}, {"time_spent": 4929, "selection": "B", "triplet_id": 15}, {"time_spent": 3243, "selection": "B", "triplet_id": 16}, {"time_spent": 8707, "selection": "A", "triplet_id": 17}, {"time_spent": 7022, "selection": "A", "triplet_id": 18}, {"time_spent": 8169, "selection": "A", "triplet_id": 19}, {"time_spent": 5956, "selection": "B", "triplet_id": 20}, {"time_spent": 5822, "selection": "B", "triplet_id": 21}, {"time_spent": 4013, "selection": "A", "triplet_id": 22}, {"time_spent": 4314, "selection": "B", "triplet_id": 23}, {"time_spent": 4678, "selection": "A", "triplet_id": 24}, {"time_spent": 6682, "selection": "A", "triplet_id": 25}, {"time_spent": 8910, "selection": "B", "triplet_id": 26}, {"time_spent": 6458, "selection": "B", "triplet_id": 27}, {"time_spent": 4872, "selection": "B", "triplet_id": 28}, {"time_spent": 6463, "selection": "A", "triplet_id": 29}, {"time_spent": 4719, "selection": "A", "triplet_id": 30}, {"time_spent": 3476, "selection": "B", "triplet_id": 31}, {"time_spent": 6377, "selection": "A", "triplet_id": 32}, {"time_spent": 3632, "selection": "A", "triplet_id": 33}, {"time_spent": 3582, "selection": "B", "triplet_id": 34}, {"time_spent": 5978, "selection": "A", "triplet_id": 35}, {"time_spent": 3805, "selection": "B", "triplet_id": 36}, {"time_spent": 5386, "selection": "B", "triplet_id": 37}, {"time_spent": 5680, "selection": "A", "triplet_id": 38}, {"time_spent": 4616, "selection": "A", "triplet_id": 39}, {"time_spent": 5896, "selection": "B", "triplet_id": 40}, {"time_spent": 4883, "selection": "A", "triplet_id": 41}, {"time_spent": 4035, "selection": "B", "triplet_id": 42}, {"time_spent": 7742, "selection": "A", "triplet_id": 43}, {"time_spent": 5666, "selection": "B", "triplet_id": 44}, {"time_spent": 5089, "selection": "B", "triplet_id": 45}, {"time_spent": 5480, "selection": "A", "triplet_id": 46}, {"time_spent": 5025, "selection": "A", "triplet_id": 47}, {"time_spent": 3927, "selection": "B", "triplet_id": 48}, {"time_spent": 5987, "selection": "B", "triplet_id": 49}, {"time_spent": 3511, "selection": "B", "triplet_id": 50}, {"time_spent": 5176, "selection": "A", "triplet_id": 51}, {"time_spent": 5650, "selection": "A", "triplet_id": 52}, {"time_spent": 5048, "selection": "A", "triplet_id": 53}, {"time_spent": 4934, "selection": "A", "triplet_id": 54}, {"time_spent": 3683, "selection": "B", "triplet_id": 55}, {"time_spent": 4651, "selection": "A", "triplet_id": 56}, {"time_spent": 13085, "selection": "B", "triplet_id": 57}, {"time_spent": 5275, "selection": "B", "triplet_id": 58}, {"time_spent": 4003, "selection": "A", "triplet_id": 59}], "gen": "M"}
{"gui_kwd": "3", "assignmentId": "7", "gd_kwd": "3", "easy_acc": "0.7142857142857143", "train_acc": "1", "output": [{"time_spent": 11638, "selection": "B", "triplet_id": 0}, {"time_spent": 19509, "selection": "B", "triplet_id": 1}, {"time_spent": 5071, "selection": "A", "triplet_id": 2}, {"time_spent": 2536, "selection": "A", "triplet_id": 3}, {"time_spent": 4758, "selection": "B", "triplet_id": 4}, {"time_spent": 7816, "selection": "A", "triplet_id": 5}, {"time_spent": 10895, "selection": "B", "triplet_id": 6}, {"time_spent": 4549, "selection": "A", "triplet_id": 7}, {"time_spent": 2372, "selection": "B", "triplet_id": 8}, {"time_spent": 3579, "selection": "A", "triplet_id": 9}, {"time_spent": 5687, "selection": "B", "triplet_id": 10}, {"time_spent": 5194, "selection": "A", "triplet_id": 11}, {"time_spent": 5686, "selection": "B", "triplet_id": 12}, {"time_spent": 5396, "selection": "B", "triplet_id": 13}, {"time_spent": 5740, "selection": "A", "triplet_id": 14}, {"time_spent": 5586, "selection": "B", "triplet_id": 15}, {"time_spent": 19013, "selection": "A", "triplet_id": 16}, {"time_spent": 4073, "selection": "A", "triplet_id": 17}, {"time_spent": 20941, "selection": "B", "triplet_id": 18}, {"time_spent": 4314, "selection": "A", "triplet_id": 19}, {"time_spent": 3275, "selection": "A", "triplet_id": 20}, {"time_spent": 3034, "selection": "B", "triplet_id": 21}, {"time_spent": 6707, "selection": "B", "triplet_id": 22}, {"time_spent": 11550, "selection": "A", "triplet_id": 23}, {"time_spent": 3131, "selection": "B", "triplet_id": 24}, {"time_spent": 2659, "selection": "A", "triplet_id": 25}, {"time_spent": 4889, "selection": "B", "triplet_id": 26}, {"time_spent": 3371, "selection": "A", "triplet_id": 27}, {"time_spent": 3937, "selection": "A", "triplet_id": 28}, {"time_spent": 2222, "selection": "A", "triplet_id": 29}, {"time_spent": 5100, "selection": "A", "triplet_id": 30}, {"time_spent": 4728, "selection": "A", "triplet_id": 31}, {"time_spent": 2010, "selection": "B", "triplet_id": 32}, {"time_spent": 33265, "selection": "B", "triplet_id": 33}, {"time_spent": 5023, "selection": "A", "triplet_id": 34}, {"time_spent": 2463, "selection": "A", "triplet_id": 35}, {"time_spent": 2223, "selection": "A", "triplet_id": 36}, {"time_spent": 3650, "selection": "B", "triplet_id": 37}, {"time_spent": 5754, "selection": "A", "triplet_id": 38}, {"time_spent": 34896, "selection": "A", "triplet_id": 39}, {"time_spent": 4163, "selection": "B", "triplet_id": 40}, {"time_spent": 2012, "selection": "B", "triplet_id": 41}, {"time_spent": 2239, "selection": "A", "triplet_id": 42}, {"time_spent": 3376, "selection": "B", "triplet_id": 43}, {"time_spent": 3266, "selection": "B", "triplet_id": 44}, {"time_spent": 8975, "selection": "A", "triplet_id": 45}, {"time_spent": 2731, "selection": "B", "triplet_id": 46}, {"time_spent": 5861, "selection": "A", "triplet_id": 47}, {"time_spent": 8570, "selection": "A", "triplet_id": 48}, {"time_spent": 4016, "selection": "A", "triplet_id": 49}, {"time_spent": 3414, "selection": "A", "triplet_id": 50}, {"time_spent": 1911, "selection": "B", "triplet_id": 51}, {"time_spent": 5934, "selection": "A", "triplet_id": 52}, {"time_spent": 7896, "selection": "B", "triplet_id": 53}, {"time_spent": 2591, "selection": "B", "triplet_id": 54}, {"time_spent": 9351, "selection": "B", "triplet_id": 55}, {"time_spent": 11104, "selection": "B", "triplet_id": 56}, {"time_spent": 2977, "selection": "A", "triplet_id": 57}, {"time_spent": 3524, "selection": "B", "triplet_id": 58}, {"time_spent": 2094, "selection": "B", "triplet_id": 59}], "gen": "M"}
{"gui_kwd": "3", "assignmentId": "6", "gd_kwd": "2", "easy_acc": "0.7142857142857143", "train_acc": "1", "output": [{"time_spent": 12801, "selection": "A", "triplet_id": 0}, {"time_spent": 4359, "selection": "A", "triplet_id": 1}, {"time_spent": 11170, "selection": "A", "triplet_id": 2}, {"time_spent": 9960, "selection": "A", "triplet_id": 3}, {"time_spent": 6327, "selection": "B", "triplet_id": 4}, {"time_spent": 3475, "selection": "A", "triplet_id": 5}, {"time_spent": 4645, "selection": "B", "triplet_id": 6}, {"time_spent": 3467, "selection": "B", "triplet_id": 7}, {"time_spent": 6190, "selection": "B", "triplet_id": 8}, {"time_spent": 4506, "selection": "A", "triplet_id": 9}, {"time_spent": 4826, "selection": "A", "triplet_id": 10}, {"time_spent": 9715, "selection": "B", "triplet_id": 11}, {"time_spent": 13418, "selection": "A", "triplet_id": 12}, {"time_spent": 5728, "selection": "B", "triplet_id": 13}, {"time_spent": 3090, "selection": "B", "triplet_id": 14}, {"time_spent": 3759, "selection": "A", "triplet_id": 15}, {"time_spent": 5246, "selection": "A", "triplet_id": 16}, {"time_spent": 8932, "selection": "B", "triplet_id": 17}, {"time_spent": 9209, "selection": "A", "triplet_id": 18}, {"time_spent": 6388, "selection": "B", "triplet_id": 19}, {"time_spent": 5105, "selection": "B", "triplet_id": 20}, {"time_spent": 3627, "selection": "A", "triplet_id": 21}, {"time_spent": 8141, "selection": "B", "triplet_id": 22}, {"time_spent": 17127, "selection": "B", "triplet_id": 23}, {"time_spent": 4504, "selection": "B", "triplet_id": 24}, {"time_spent": 7521, "selection": "A", "triplet_id": 25}, {"time_spent": 3659, "selection": "B", "triplet_id": 26}, {"time_spent": 5155, "selection": "A", "triplet_id": 27}, {"time_spent": 4773, "selection": "B", "triplet_id": 28}, {"time_spent": 3594, "selection": "B", "triplet_id": 29}, {"time_spent": 3903, "selection": "A", "triplet_id": 30}, {"time_spent": 4176, "selection": "A", "triplet_id": 31}, {"time_spent": 3734, "selection": "A", "triplet_id": 32}, {"time_spent": 3582, "selection": "B", "triplet_id": 33}, {"time_spent": 5289, "selection": "A", "triplet_id": 34}, {"time_spent": 14674, "selection": "B", "triplet_id": 35}, {"time_spent": 9546, "selection": "A", "triplet_id": 36}, {"time_spent": 3362, "selection": "B", "triplet_id": 37}, {"time_spent": 6373, "selection": "A", "triplet_id": 38}, {"time_spent": 6834, "selection": "A", "triplet_id": 39}, {"time_spent": 4251, "selection": "A", "triplet_id": 40}, {"time_spent": 4968, "selection": "B", "triplet_id": 41}, {"time_spent": 5842, "selection": "A", "triplet_id": 42}, {"time_spent": 8817, "selection": "A", "triplet_id": 43}, {"time_spent": 3326, "selection": "A", "triplet_id": 44}, {"time_spent": 8975, "selection": "B", "triplet_id": 45}, {"time_spent": 6850, "selection": "A", "triplet_id": 46}, {"time_spent": 6915, "selection": "A", "triplet_id": 47}, {"time_spent": 3328, "selection": "A", "triplet_id": 48}, {"time_spent": 7940, "selection": "A", "triplet_id": 49}, {"time_spent": 8368, "selection": "A", "triplet_id": 50}, {"time_spent": 4248, "selection": "A", "triplet_id": 51}, {"time_spent": 4200, "selection": "A", "triplet_id": 52}, {"time_spent": 4952, "selection": "A", "triplet_id": 53}, {"time_spent": 3821, "selection": "A", "triplet_id": 54}, {"time_spent": 3416, "selection": "A", "triplet_id": 55}, {"time_spent": 6742, "selection": "A", "triplet_id": 56}, {"time_spent": 6659, "selection": "A", "triplet_id": 57}, {"time_spent": 9317, "selection": "A", "triplet_id": 58}, {"time_spent": 4499, "selection": "A", "triplet_id": 59}], "gen": "F"}
{"gui_kwd": "3", "assignmentId": "9", "gd_kwd": "3", "easy_acc": "0.8571428571428571", "train_acc": "1", "output": [{"time_spent": 79265, "selection": "A", "triplet_id": 0}, {"time_spent": 7912, "selection": "B", "triplet_id": 1}, {"time_spent": 8080, "selection": "A", "triplet_id": 2}, {"time_spent": 18065, "selection": "A", "triplet_id": 3}, {"time_spent": 5951, "selection": "B", "triplet_id": 4}, {"time_spent": 6592, "selection": "A", "triplet_id": 5}, {"time_spent": 11920, "selection": "A", "triplet_id": 6}, {"time_spent": 11623, "selection": "B", "triplet_id": 7}, {"time_spent": 1968, "selection": "B", "triplet_id": 8}, {"time_spent": 12744, "selection": "A", "triplet_id": 9}, {"time_spent": 4688, "selection": "A", "triplet_id": 10}, {"time_spent": 11001, "selection": "A", "triplet_id": 11}, {"time_spent": 5047, "selection": "A", "triplet_id": 12}, {"time_spent": 3744, "selection": "A", "triplet_id": 13}, {"time_spent": 10905, "selection": "A", "triplet_id": 14}, {"time_spent": 3479, "selection": "A", "triplet_id": 15}, {"time_spent": 2201, "selection": "A", "triplet_id": 16}, {"time_spent": 8160, "selection": "A", "triplet_id": 17}, {"time_spent": 4966, "selection": "B", "triplet_id": 18}, {"time_spent": 10194, "selection": "A", "triplet_id": 19}, {"time_spent": 5528, "selection": "A", "triplet_id": 20}, {"time_spent": 7584, "selection": "A", "triplet_id": 21}, {"time_spent": 2313, "selection": "A", "triplet_id": 22}, {"time_spent": 3887, "selection": "A", "triplet_id": 23}, {"time_spent": 1904, "selection": "A", "triplet_id": 24}, {"time_spent": 1856, "selection": "B", "triplet_id": 25}, {"time_spent": 2993, "selection": "B", "triplet_id": 26}, {"time_spent": 2639, "selection": "B", "triplet_id": 27}, {"time_spent": 1832, "selection": "A", "triplet_id": 28}, {"time_spent": 2305, "selection": "A", "triplet_id": 29}, {"time_spent": 4720, "selection": "A", "triplet_id": 30}, {"time_spent": 5479, "selection": "B", "triplet_id": 31}, {"time_spent": 4368, "selection": "A", "triplet_id": 32}, {"time_spent": 4456, "selection": "B", "triplet_id": 33}, {"time_spent": 3625, "selection": "B", "triplet_id": 34}, {"time_spent": 1974, "selection": "A", "triplet_id": 35}, {"time_spent": 2042, "selection": "A", "triplet_id": 36}, {"time_spent": 3216, "selection": "B", "triplet_id": 37}, {"time_spent": 2623, "selection": "A", "triplet_id": 38}, {"time_spent": 11152, "selection": "A", "triplet_id": 39}, {"time_spent": 7400, "selection": "A", "triplet_id": 40}, {"time_spent": 3640, "selection": "B", "triplet_id": 41}, {"time_spent": 1560, "selection": "B", "triplet_id": 42}, {"time_spent": 2977, "selection": "B", "triplet_id": 43}, {"time_spent": 4023, "selection": "B", "triplet_id": 44}, {"time_spent": 4329, "selection": "B", "triplet_id": 45}, {"time_spent": 3904, "selection": "A", "triplet_id": 46}, {"time_spent": 3295, "selection": "B", "triplet_id": 47}, {"time_spent": 4929, "selection": "B", "triplet_id": 48}, {"time_spent": 5904, "selection": "B", "triplet_id": 49}, {"time_spent": 4416, "selection": "B", "triplet_id": 50}, {"time_spent": 4520, "selection": "B", "triplet_id": 51}, {"time_spent": 1848, "selection": "A", "triplet_id": 52}, {"time_spent": 4400, "selection": "A", "triplet_id": 53}, {"time_spent": 2967, "selection": "A", "triplet_id": 54}, {"time_spent": 7361, "selection": "B", "triplet_id": 55}, {"time_spent": 3296, "selection": "A", "triplet_id": 56}, {"time_spent": 3984, "selection": "A", "triplet_id": 57}, {"time_spent": 2280, "selection": "A", "triplet_id": 58}, {"time_spent": 6330, "selection": "B", "triplet_id": 59}], "gen": "M"}
{"gui_kwd": "3", "assignmentId": "8", "gd_kwd": "2", "easy_acc": "0.7142857142857143", "train_acc": "0.75", "output": [{"time_spent": 14259, "selection": "B", "triplet_id": 0}, {"time_spent": 3289, "selection": "B", "triplet_id": 1}, {"time_spent": 2128, "selection": "B", "triplet_id": 2}, {"time_spent": 3512, "selection": "B", "triplet_id": 3}, {"time_spent": 3768, "selection": "A", "triplet_id": 4}, {"time_spent": 5241, "selection": "A", "triplet_id": 5}, {"time_spent": 3761, "selection": "A", "triplet_id": 6}, {"time_spent": 8975, "selection": "B", "triplet_id": 7}, {"time_spent": 2288, "selection": "B", "triplet_id": 8}, {"time_spent": 4554, "selection": "A", "triplet_id": 9}, {"time_spent": 3543, "selection": "B", "triplet_id": 10}, {"time_spent": 2097, "selection": "B", "triplet_id": 11}, {"time_spent": 4192, "selection": "B", "triplet_id": 12}, {"time_spent": 4320, "selection": "A", "triplet_id": 13}, {"time_spent": 20122, "selection": "B", "triplet_id": 14}, {"time_spent": 2520, "selection": "A", "triplet_id": 15}, {"time_spent": 2736, "selection": "A", "triplet_id": 16}, {"time_spent": 2713, "selection": "B", "triplet_id": 17}, {"time_spent": 4814, "selection": "A", "triplet_id": 18}, {"time_spent": 2385, "selection": "A", "triplet_id": 19}, {"time_spent": 13241, "selection": "B", "triplet_id": 20}, {"time_spent": 15225, "selection": "A", "triplet_id": 21}, {"time_spent": 4305, "selection": "A", "triplet_id": 22}, {"time_spent": 2271, "selection": "A", "triplet_id": 23}, {"time_spent": 5842, "selection": "A", "triplet_id": 24}, {"time_spent": 6271, "selection": "A", "triplet_id": 25}, {"time_spent": 7354, "selection": "B", "triplet_id": 26}, {"time_spent": 2599, "selection": "A", "triplet_id": 27}, {"time_spent": 2376, "selection": "B", "triplet_id": 28}, {"time_spent": 3273, "selection": "A", "triplet_id": 29}, {"time_spent": 7217, "selection": "B", "triplet_id": 30}, {"time_spent": 3137, "selection": "B", "triplet_id": 31}, {"time_spent": 6423, "selection": "B", "triplet_id": 32}, {"time_spent": 2368, "selection": "B", "triplet_id": 33}, {"time_spent": 2288, "selection": "B", "triplet_id": 34}, {"time_spent": 6057, "selection": "B", "triplet_id": 35}, {"time_spent": 3425, "selection": "A", "triplet_id": 36}, {"time_spent": 4015, "selection": "A", "triplet_id": 37}, {"time_spent": 2185, "selection": "B", "triplet_id": 38}, {"time_spent": 1935, "selection": "B", "triplet_id": 39}, {"time_spent": 6401, "selection": "A", "triplet_id": 40}, {"time_spent": 2968, "selection": "A", "triplet_id": 41}, {"time_spent": 2104, "selection": "B", "triplet_id": 42}, {"time_spent": 3568, "selection": "B", "triplet_id": 43}, {"time_spent": 5209, "selection": "A", "triplet_id": 44}, {"time_spent": 4593, "selection": "A", "triplet_id": 45}, {"time_spent": 1752, "selection": "A", "triplet_id": 46}, {"time_spent": 9495, "selection": "B", "triplet_id": 47}, {"time_spent": 2281, "selection": "A", "triplet_id": 48}, {"time_spent": 8185, "selection": "B", "triplet_id": 49}, {"time_spent": 3295, "selection": "B", "triplet_id": 50}, {"time_spent": 2160, "selection": "A", "triplet_id": 51}, {"time_spent": 2257, "selection": "A", "triplet_id": 52}, {"time_spent": 2616, "selection": "B", "triplet_id": 53}, {"time_spent": 1745, "selection": "B", "triplet_id": 54}, {"time_spent": 1536, "selection": "B", "triplet_id": 55}, {"time_spent": 2456, "selection": "A", "triplet_id": 56}, {"time_spent": 2360, "selection": "B", "triplet_id": 57}, {"time_spent": 2400, "selection": "B", "triplet_id": 58}, {"time_spent": 1913, "selection": "A", "triplet_id": 59}], "gen": "F"}
{"gui_kwd": "3", "assignmentId": "10", "gd_kwd": "3", "easy_acc": "0.7142857142857143", "train_acc": "0.75", "output": [{"time_spent": 2980, "selection": "B", "triplet_id": 0}, {"time_spent": 2983, "selection": "B", "triplet_id": 1}, {"time_spent": 3000, "selection": "B", "triplet_id": 2}, {"time_spent": 3839, "selection": "A", "triplet_id": 3}, {"time_spent": 2056, "selection": "A", "triplet_id": 4}, {"time_spent": 1856, "selection": "A", "triplet_id": 5}, {"time_spent": 2840, "selection": "A", "triplet_id": 6}, {"time_spent": 4160, "selection": "B", "triplet_id": 7}, {"time_spent": 2176, "selection": "B", "triplet_id": 8}, {"time_spent": 2208, "selection": "B", "triplet_id": 9}, {"time_spent": 2057, "selection": "A", "triplet_id": 10}, {"time_spent": 1903, "selection": "A", "triplet_id": 11}, {"time_spent": 4309, "selection": "A", "triplet_id": 12}, {"time_spent": 2563, "selection": "A", "triplet_id": 13}, {"time_spent": 2536, "selection": "B", "triplet_id": 14}, {"time_spent": 2953, "selection": "A", "triplet_id": 15}, {"time_spent": 3535, "selection": "B", "triplet_id": 16}, {"time_spent": 3618, "selection": "B", "triplet_id": 17}, {"time_spent": 2550, "selection": "A", "triplet_id": 18}, {"time_spent": 2177, "selection": "A", "triplet_id": 19}, {"time_spent": 2071, "selection": "B", "triplet_id": 20}, {"time_spent": 2993, "selection": "A", "triplet_id": 21}, {"time_spent": 2873, "selection": "B", "triplet_id": 22}, {"time_spent": 1879, "selection": "B", "triplet_id": 23}, {"time_spent": 2184, "selection": "A", "triplet_id": 24}, {"time_spent": 2304, "selection": "A", "triplet_id": 25}, {"time_spent": 1952, "selection": "B", "triplet_id": 26}, {"time_spent": 2261, "selection": "A", "triplet_id": 27}, {"time_spent": 2780, "selection": "A", "triplet_id": 28}, {"time_spent": 1655, "selection": "B", "triplet_id": 29}, {"time_spent": 3464, "selection": "A", "triplet_id": 30}, {"time_spent": 2105, "selection": "B", "triplet_id": 31}, {"time_spent": 3727, "selection": "A", "triplet_id": 32}, {"time_spent": 2056, "selection": "A", "triplet_id": 33}, {"time_spent": 2400, "selection": "B", "triplet_id": 34}, {"time_spent": 2211, "selection": "A", "triplet_id": 35}, {"time_spent": 2397, "selection": "A", "triplet_id": 36}, {"time_spent": 2927, "selection": "B", "triplet_id": 37}, {"time_spent": 1961, "selection": "B", "triplet_id": 38}, {"time_spent": 2977, "selection": "A", "triplet_id": 39}, {"time_spent": 2811, "selection": "A", "triplet_id": 40}, {"time_spent": 2132, "selection": "A", "triplet_id": 41}, {"time_spent": 1944, "selection": "B", "triplet_id": 42}, {"time_spent": 2883, "selection": "A", "triplet_id": 43}, {"time_spent": 2461, "selection": "A", "triplet_id": 44}, {"time_spent": 3210, "selection": "B", "triplet_id": 45}, {"time_spent": 1799, "selection": "A", "triplet_id": 46}, {"time_spent": 2432, "selection": "B", "triplet_id": 47}, {"time_spent": 2375, "selection": "B", "triplet_id": 48}, {"time_spent": 2344, "selection": "A", "triplet_id": 49}, {"time_spent": 1751, "selection": "B", "triplet_id": 50}, {"time_spent": 2202, "selection": "B", "triplet_id": 51}, {"time_spent": 2568, "selection": "A", "triplet_id": 52}, {"time_spent": 2792, "selection": "A", "triplet_id": 53}, {"time_spent": 2337, "selection": "B", "triplet_id": 54}, {"time_spent": 4929, "selection": "A", "triplet_id": 55}, {"time_spent": 2246, "selection": "A", "triplet_id": 56}, {"time_spent": 2112, "selection": "B", "triplet_id": 57}, {"time_spent": 2000, "selection": "B", "triplet_id": 58}, {"time_spent": 3250, "selection": "A", "triplet_id": 59}], "gen": "M"}
