{"gui_kwd": "3", "assignmentId": "", "train_acc": "1", "easy_acc": "0", "output": [{"time_spent": 1727, "selection": "A", "triplet_id": 0}, {"time_spent": 2176, "selection": "A", "triplet_id": 1}, {"time_spent": 607, "selection": "B", "triplet_id": 2}, {"time_spent": 697, "selection": "A", "triplet_id": 3}, {"time_spent": 624, "selection": "B", "triplet_id": 4}, {"time_spent": 527, "selection": "B", "triplet_id": 5}, {"time_spent": 536, "selection": "B", "triplet_id": 6}, {"time_spent": 512, "selection": "B", "triplet_id": 7}, {"time_spent": 488, "selection": "B", "triplet_id": 8}, {"time_spent": 464, "selection": "B", "triplet_id": 9}, {"time_spent": 473, "selection": "B", "triplet_id": 10}, {"time_spent": 487, "selection": "B", "triplet_id": 11}, {"time_spent": 473, "selection": "B", "triplet_id": 12}, {"time_spent": 504, "selection": "B", "triplet_id": 13}, {"time_spent": 632, "selection": "B", "triplet_id": 14}, {"time_spent": 1264, "selection": "B", "triplet_id": 15}, {"time_spent": 1431, "selection": "B", "triplet_id": 16}, {"time_spent": 528, "selection": "B", "triplet_id": 17}, {"time_spent": 544, "selection": "B", "triplet_id": 18}, {"time_spent": 624, "selection": "B", "triplet_id": 19}, {"time_spent": 601, "selection": "B", "triplet_id": 20}, {"time_spent": 2984, "selection": "B", "triplet_id": 21}], "gen": "M", "gd_kwd": "2"}{"gui_kwd": "2", "assignmentId": "", "train_acc": "1", "easy_acc": "0", "output": [{"time_spent": 3199, "selection": "B", "triplet_id": 0}, {"time_spent": 2568, "selection": "A", "triplet_id": 1}], "gen": "F", "gd_kwd": "3"}{"gui_kwd": "3", "assignmentId": "", "train_acc": "1", "gd_kwd": "1", "output": [{"time_spent": 686, "selection": "B", "triplet_id": 0}, {"time_spent": 664, "selection": "A", "triplet_id": 1}], "gen": "F"}{"gui_kwd": "2", "assignmentId": "", "train_acc": "1", "gd_kwd": "2", "output": [{"time_spent": 895, "selection": "B", "triplet_id": 0}, {"time_spent": 752, "selection": "A", "triplet_id": 1}], "gen": "F"}
